bottle.py
bottle_dev-0.13.2.data/scripts/bottle.py
bottle_dev-0.13.2.dist-info/METADATA
bottle_dev-0.13.2.dist-info/WHEEL
bottle_dev-0.13.2.dist-info/top_level.txt
bottle_dev-0.13.2.dist-info/RECORD
